robosystems_mcp/__init__.py
robosystems_mcp/database.py
robosystems_mcp/server.py
robosystems_mcp/tools.py
robosystems_mcp-0.2.10.dist-info/METADATA
robosystems_mcp-0.2.10.dist-info/WHEEL
robosystems_mcp-0.2.10.dist-info/entry_points.txt
robosystems_mcp-0.2.10.dist-info/RECORD
