Metadata-Version: 2.4
Name: robosystems-mcp
Version: 0.2.10
Summary: A simple Neo4j MCP server
Requires-Python: >=3.12
Requires-Dist: aiohttp>=3.8.0
Requires-Dist: mcp>=1.6.0
Provides-Extra: dev
Requires-Dist: mcp[cli]>=1.6.0; extra == 'dev'
Requires-Dist: pyright>=1.1.402; extra == 'dev'
Requires-Dist: pytest-asyncio>=0.26.0; extra == 'dev'
Requires-Dist: pytest>=8.3.5; extra == 'dev'
Requires-Dist: ruff>=0.11.4; extra == 'dev'
